AESEncryptor_heureka_code/AESFileEncryptor.py
AESEncryptor_heureka_code/AESTextEncryptor.py
AESEncryptor_heureka_code/__init__.py
AESEncryptor_heureka_code/Exceptions/FileExceptions.py
AESEncryptor_heureka_code/Exceptions/PasswordExceptions.py
AESEncryptor_heureka_code/Exceptions/TextExceptions.py
AESEncryptor_heureka_code/Exceptions/__init__.py
AESEncryptor_heureka_code-1.3.0.dist-info/LICENSE.txt
AESEncryptor_heureka_code-1.3.0.dist-info/METADATA
AESEncryptor_heureka_code-1.3.0.dist-info/WHEEL
AESEncryptor_heureka_code-1.3.0.dist-info/top_level.txt
AESEncryptor_heureka_code-1.3.0.dist-info/RECORD
