Metadata-Version: 2.1
Name: AESEncryptor-heureka-code
Version: 1.3.0
Summary: Verschlüsselt Datein und Texte mit AES
Home-page: https://github.com/heureka-code/AESEncryptor-heureka-code
Author: heureka-code
License: MIT
Download-URL: https://github.com/heureka-code/AESEncryptor-heureka-code/archive/refs/tags/1.3.0.tar.gz
Platform: UNKNOWN
License-File: LICENSE.txt
Requires-Dist: pycryptodome
